nacos_starter/__init__.py
nacos_starter/constants.py
nacos_starter/exception.py
nacos_starter/func_fuse.py
nacos_starter/nacos.py
nacos_starter/util.py
nacos_starter-1.1.0.dist-info/LICENSE
nacos_starter-1.1.0.dist-info/METADATA
nacos_starter-1.1.0.dist-info/WHEEL
nacos_starter-1.1.0.dist-info/top_level.txt
nacos_starter-1.1.0.dist-info/RECORD
