Metadata-Version: 2.1
Name: nacos-starter
Version: 1.1.0
Summary: Nacos starter for python
Author: chizongyang
Author-email: chizongyang@aliyun.com
Project-URL: Bug Tracker, https://github.com/asdw741111/nacos-py-starter/issues
Project-URL: Source Code, https://github.com/asdw741111/nacos-py-starter
Classifier: Programming Language :: Python :: 3
Classifier: License :: OSI Approved :: MIT License
Classifier: Operating System :: OS Independent
Requires-Python: >=3.6
License-File: LICENSE
Requires-Dist: pyyaml==6.0.2
